{
    "points": [
        {"x": 121.686, "y": 157.738, "label": 0},
        {"x": 119.686, "y": 174.738, "label": 0},
        {"x": 112.686, "y": 166.738, "label": 0},
        {"x": 113.686, "y": 160.738, "label": 0},
        {"x": 114.686, "y": 171.738, "label": 0},
        {"x": 105.686, "y": 161.738, "label": 0},
        {"x": 118.686, "y": 160.738, "label": 0},
        {"x": 112.686, "y": 163.738, "label": 0},
        {"x": 111.686, "y": 174.738, "label": 0},
        {"x": 121.686, "y": 171.738, "label": 0},
        {"x": 117.686, "y": 174.738, "label": 0},
        {"x": 125.686, "y": 157.738, "label": 0},
        {"x": 119.686, "y": 166.738, "label": 0},
        {"x": 120.686, "y": 164.738, "label": 0},
        {"x": 110.686, "y": 170.738, "label": 0},
        {"x": 117.686, "y": 156.738, "label": 0},
        {"x": 111.686, "y": 156.738, "label": 0},
        {"x": 125.686, "y": 161.738, "label": 0},
        {"x": 119.686, "y": 168.738, "label": 0},
        {"x": 112.686, "y": 156.738, "label": 0},
        {"x": 115.686, "y": 171.738, "label": 0},
        {"x": 113.686, "y": 160.738, "label": 0},
        {"x": 114.686, "y": 156.738, "label": 0},
        {"x": 120.686, "y": 161.738, "label": 0},
        {"x": 113.686, "y": 159.738, "label": 0},
        {"x": 117.686, "y": 161.738, "label": 0},
        {"x": 121.686, "y": 162.738, "label": 0},
        {"x": 111.686, "y": 168.738, "label": 0},
        {"x": 106.686, "y": 173.738, "label": 0},
        {"x": 115.686, "y": 156.738, "label": 0},
        {"x": 111.686, "y": 167.738, "label": 0},
        {"x": 120.686, "y": 165.738, "label": 0},
        {"x": 119.686, "y": 164.738, "label": 0},
        {"x": 116.686, "y": 162.738, "label": 0},
        {"x": 115.686, "y": 169.738, "label": 0},
        {"x": 106.686, "y": 157.738, "label": 0},
        {"x": 113.686, "y": 157.738, "label": 0},
        {"x": 107.686, "y": 173.738, "label": 0},
        {"x": 117.686, "y": 154.738, "label": 0},
        {"x": 108.686, "y": 155.738, "label": 0},
        {"x": 113.686, "y": 164.738, "label": 0},
        {"x": 114.686, "y": 157.738, "label": 0},
        {"x": 105.686, "y": 170.738, "label": 0},
        {"x": 109.686, "y": 157.738, "label": 0},
        {"x": 125.686, "y": 160.738, "label": 0},
        {"x": 125.686, "y": 159.738, "label": 0},
        {"x": 107.686, "y": 165.738, "label": 0},
        {"x": 121.686, "y": 166.738, "label": 0},
        {"x": 117.686, "y": 169.738, "label": 0},
        {"x": 123.686, "y": 155.738, "label": 0},
        {"x": 111.686, "y": 175.738, "label": 0},
        {"x": 118.686, "y": 160.738, "label": 0},
        {"x": 121.686, "y": 163.738, "label": 0},
        {"x": 115.686, "y": 158.738, "label": 0},
        {"x": 114.686, "y": 167.738, "label": 0},
        {"x": 126.686, "y": 174.738, "label": 0},
        {"x": 115.686, "y": 154.738, "label": 0},
        {"x": 123.686, "y": 163.738, "label": 0},
        {"x": 122.686, "y": 167.738, "label": 0},
        {"x": 109.686, "y": 162.738, "label": 0},
        {"x": 121.686, "y": 170.738, "label": 0},
        {"x": 119.686, "y": 174.738, "label": 0},
        {"x": 117.686, "y": 159.738, "label": 0},
        {"x": 112.686, "y": 174.738, "label": 0},
        {"x": 123.686, "y": 175.738, "label": 0},
        {"x": 108.686, "y": 171.738, "label": 0},
        {"x": 124.686, "y": 168.738, "label": 0},
        {"x": 118.686, "y": 156.738, "label": 0},
        {"x": 110.686, "y": 159.738, "label": 0},
        {"x": 117.686, "y": 168.738, "label": 0},
        {"x": 123.686, "y": 168.738, "label": 0},
        {"x": 105.686, "y": 154.738, "label": 0},
        {"x": 120.686, "y": 157.738, "label": 0},
        {"x": 112.686, "y": 167.738, "label": 0},
        {"x": 114.686, "y": 158.738, "label": 0},
        {"x": 106.686, "y": 174.738, "label": 0},
        {"x": 108.686, "y": 168.738, "label": 0},
        {"x": 109.686, "y": 173.738, "label": 0},
        {"x": 125.686, "y": 164.738, "label": 0},
        {"x": 120.686, "y": 167.738, "label": 0},
        {"x": 123.686, "y": 170.738, "label": 0},
        {"x": 120.686, "y": 174.738, "label": 0},
        {"x": 109.686, "y": 169.738, "label": 0},
        {"x": 125.686, "y": 165.738, "label": 0},
        {"x": 124.686, "y": 154.738, "label": 0},
        {"x": 111.686, "y": 155.738, "label": 0},
        {"x": 108.686, "y": 158.738, "label": 0},
        {"x": 111.686, "y": 156.738, "label": 0},
        {"x": 110.686, "y": 168.738, "label": 0},
        {"x": 124.686, "y": 165.738, "label": 0},
        {"x": 123.686, "y": 165.738, "label": 0},
        {"x": 111.686, "y": 154.738, "label": 0},
        {"x": 106.686, "y": 165.738, "label": 0},
        {"x": 115.686, "y": 173.738, "label": 0},
        {"x": 110.686, "y": 165.738, "label": 0},
        {"x": 110.686, "y": 154.738, "label": 0},
        {"x": 125.686, "y": 169.738, "label": 0},
        {"x": 119.686, "y": 159.738, "label": 0},
        {"x": 119.686, "y": 161.738, "label": 0},
        {"x": 115.686, "y": 159.738, "label": 0},
        {"x": 125.686, "y": 163.738, "label": 0},
        {"x": 111.686, "y": 154.738, "label": 0},
        {"x": 110.686, "y": 173.738, "label": 0},
        {"x": 119.686, "y": 164.738, "label": 0},
        {"x": 110.686, "y": 158.738, "label": 0},
        {"x": 113.686, "y": 161.738, "label": 0},
        {"x": 115.686, "y": 169.738, "label": 0},
        {"x": 112.686, "y": 169.738, "label": 0},
        {"x": 124.686, "y": 156.738, "label": 0},
        {"x": 106.686, "y": 165.738, "label": 0},
        {"x": 124.686, "y": 173.738, "label": 0},
        {"x": 110.686, "y": 169.738, "label": 0},
        {"x": 115.686, "y": 162.738, "label": 0},
        {"x": 121.686, "y": 170.738, "label": 0},
        {"x": 113.686, "y": 171.738, "label": 0},
        {"x": 110.686, "y": 174.738, "label": 0},
        {"x": 117.686, "y": 162.738, "label": 0},
        {"x": 123.686, "y": 174.738, "label": 0},
        {"x": 111.686, "y": 164.738, "label": 0},
        {"x": 116.686, "y": 160.738, "label": 0},
        {"x": 105.686, "y": 165.738, "label": 0},
        {"x": 126.686, "y": 175.738, "label": 0},
        {"x": 116.686, "y": 165.738, "label": 0},
        {"x": 188.137, "y": 137.25, "label": 1},
        {"x": 192.137, "y": 132.25, "label": 1},
        {"x": 186.137, "y": 146.25, "label": 1},
        {"x": 189.137, "y": 139.25, "label": 1},
        {"x": 196.137, "y": 135.25, "label": 1},
        {"x": 194.137, "y": 144.25, "label": 1},
        {"x": 184.137, "y": 141.25, "label": 1},
        {"x": 184.137, "y": 131.25, "label": 1},
        {"x": 195.137, "y": 146.25, "label": 1},
        {"x": 194.137, "y": 128.25, "label": 1},
        {"x": 193.137, "y": 140.25, "label": 1},
        {"x": 184.137, "y": 146.25, "label": 1},
        {"x": 183.137, "y": 144.25, "label": 1},
        {"x": 192.137, "y": 129.25, "label": 1},
        {"x": 196.137, "y": 133.25, "label": 1},
        {"x": 180.137, "y": 134.25, "label": 1},
        {"x": 187.137, "y": 141.25, "label": 1},
        {"x": 189.137, "y": 130.25, "label": 1},
        {"x": 176.137, "y": 146.25, "label": 1},
        {"x": 181.137, "y": 135.25, "label": 1},
        {"x": 179.137, "y": 138.25, "label": 1},
        {"x": 178.137, "y": 148.25, "label": 1},
        {"x": 193.137, "y": 138.25, "label": 1},
        {"x": 195.137, "y": 140.25, "label": 1},
        {"x": 186.137, "y": 139.25, "label": 1},
        {"x": 185.137, "y": 147.25, "label": 1},
        {"x": 181.137, "y": 142.25, "label": 1},
        {"x": 194.137, "y": 147.25, "label": 1},
        {"x": 186.137, "y": 139.25, "label": 1},
        {"x": 184.137, "y": 132.25, "label": 1},
        {"x": 196.137, "y": 141.25, "label": 1},
        {"x": 182.137, "y": 128.25, "label": 1},
        {"x": 181.137, "y": 134.25, "label": 1},
        {"x": 184.137, "y": 136.25, "label": 1},
        {"x": 177.137, "y": 130.25, "label": 1},
        {"x": 191.137, "y": 141.25, "label": 1},
        {"x": 187.137, "y": 130.25, "label": 1},
        {"x": 194.137, "y": 135.25, "label": 1},
        {"x": 194.137, "y": 133.25, "label": 1},
        {"x": 179.137, "y": 137.25, "label": 1},
        {"x": 181.137, "y": 137.25, "label": 1},
        {"x": 183.137, "y": 138.25, "label": 1},
        {"x": 195.137, "y": 141.25, "label": 1},
        {"x": 188.137, "y": 148.25, "label": 1},
        {"x": 189.137, "y": 141.25, "label": 1},
        {"x": 184.137, "y": 141.25, "label": 1},
        {"x": 179.137, "y": 139.25, "label": 1},
        {"x": 193.137, "y": 142.25, "label": 1},
        {"x": 183.137, "y": 144.25, "label": 1},
        {"x": 185.137, "y": 136.25, "label": 1},
        {"x": 182.137, "y": 148.25, "label": 1},
        {"x": 175.137, "y": 140.25, "label": 1},
        {"x": 192.137, "y": 139.25, "label": 1},
        {"x": 178.137, "y": 133.25, "label": 1},
        {"x": 196.137, "y": 132.25, "label": 1},
        {"x": 178.137, "y": 130.25, "label": 1},
        {"x": 175.137, "y": 140.25, "label": 1},
        {"x": 185.137, "y": 131.25, "label": 1},
        {"x": 188.137, "y": 147.25, "label": 1},
        {"x": 188.137, "y": 146.25, "label": 1},
        {"x": 187.137, "y": 138.25, "label": 1},
        {"x": 185.137, "y": 142.25, "label": 1},
        {"x": 193.137, "y": 141.25, "label": 1},
        {"x": 188.137, "y": 131.25, "label": 1},
        {"x": 193.137, "y": 142.25, "label": 1},
        {"x": 193.137, "y": 147.25, "label": 1},
        {"x": 193.137, "y": 143.25, "label": 1},
        {"x": 184.137, "y": 144.25, "label": 1},
        {"x": 185.137, "y": 129.25, "label": 1},
        {"x": 196.137, "y": 133.25, "label": 1},
        {"x": 191.137, "y": 135.25, "label": 1},
        {"x": 186.137, "y": 136.25, "label": 1},
        {"x": 192.137, "y": 141.25, "label": 1},
        {"x": 188.137, "y": 148.25, "label": 1},
        {"x": 186.137, "y": 137.25, "label": 1},
        {"x": 177.137, "y": 130.25, "label": 1},
        {"x": 194.137, "y": 128.25, "label": 1},
        {"x": 194.137, "y": 135.25, "label": 1},
        {"x": 182.137, "y": 135.25, "label": 1},
        {"x": 183.137, "y": 133.25, "label": 1},
        {"x": 194.137, "y": 143.25, "label": 1},
        {"x": 195.137, "y": 140.25, "label": 1},
        {"x": 194.137, "y": 141.25, "label": 1},
        {"x": 182.137, "y": 139.25, "label": 1},
        {"x": 185.137, "y": 147.25, "label": 1},
        {"x": 187.137, "y": 130.25, "label": 1},
        {"x": 193.137, "y": 140.25, "label": 1},
        {"x": 190.137, "y": 139.25, "label": 1},
        {"x": 195.137, "y": 135.25, "label": 1},
        {"x": 195.137, "y": 138.25, "label": 1},
        {"x": 196.137, "y": 129.25, "label": 1},
        {"x": 195.137, "y": 138.25, "label": 1},
        {"x": 180.137, "y": 129.25, "label": 1},
        {"x": 181.137, "y": 135.25, "label": 1},
        {"x": 176.137, "y": 147.25, "label": 1},
        {"x": 192.137, "y": 133.25, "label": 1},
        {"x": 180.137, "y": 142.25, "label": 1},
        {"x": 179.137, "y": 128.25, "label": 1},
        {"x": 181.137, "y": 145.25, "label": 1},
        {"x": 178.137, "y": 146.25, "label": 1},
        {"x": 183.137, "y": 133.25, "label": 1},
        {"x": 181.137, "y": 144.25, "label": 1},
        {"x": 181.137, "y": 144.25, "label": 1},
        {"x": 191.137, "y": 132.25, "label": 1},
        {"x": 176.137, "y": 139.25, "label": 1},
        {"x": 180.137, "y": 143.25, "label": 1},
        {"x": 190.137, "y": 144.25, "label": 1},
        {"x": 195.137, "y": 134.25, "label": 1},
        {"x": 192.137, "y": 134.25, "label": 1},
        {"x": 183.137, "y": 138.25, "label": 1},
        {"x": 177.137, "y": 143.25, "label": 1},
        {"x": 193.137, "y": 147.25, "label": 1},
        {"x": 181.137, "y": 137.25, "label": 1},
        {"x": 186.137, "y": 146.25, "label": 1},
        {"x": 182.137, "y": 144.25, "label": 1},
        {"x": 187.137, "y": 127.25, "label": 1},
        {"x": 191.137, "y": 136.25, "label": 1},
        {"x": 185.137, "y": 134.25, "label": 1},
        {"x": 188.137, "y": 145.25, "label": 1},
        {"x": 188.137, "y": 144.25, "label": 1},
        {"x": 191.137, "y": 143.25, "label": 1},
        {"x": 186.137, "y": 148.25, "label": 1},
        {"x": 179.137, "y": 134.25, "label": 1}
    ]
}
